ecopass/__init__.py
ecopass/cli.py
ecopass/core/record_header.py
ecopass-0.1.15.dist-info/LICENSE
ecopass-0.1.15.dist-info/METADATA
ecopass-0.1.15.dist-info/WHEEL
ecopass-0.1.15.dist-info/entry_points.txt
ecopass-0.1.15.dist-info/RECORD
