Metadata-Version: 2.1
Name: ecopass
Version: 0.1.15
Summary: This script specifically handles microfile headers sequentially.
Home-page: https://pypi.org/project/ecopass/
License: MIT
Author: yassinessadi
Author-email: yasine.esadi@gmail.com
Requires-Python: >=3.8,<4.0
Classifier: License :: OSI Approved :: MIT License
Classifier: Programming Language :: Python :: 3
Classifier: Programming Language :: Python :: 3.8
Classifier: Programming Language :: Python :: 3.9
Classifier: Programming Language :: Python :: 3.10
Classifier: Programming Language :: Python :: 3.11
Classifier: Programming Language :: Python :: 3.12
Classifier: Programming Language :: Python :: 3.13
Requires-Dist: click (>=8.1.8,<9.0.0)
Requires-Dist: pandas (==1.4.2)
Requires-Dist: psutil (>=7.0.0,<8.0.0)
Requires-Dist: pyarrow (==14.0.1)
Requires-Dist: rich (>=13.9.4,<14.0.0)
Project-URL: Repository, https://github.com/yassinessadi/ecopass
